fhir2transmart/__init__.py
fhir2transmart/__version__.py
fhir2transmart/fhir.py
fhir2transmart/fhir2transmart.py
fhir2transmart/fhir_reader.py
fhir2transmart/mapper.py
fhir2transmart-0.2.1.dist-info/LICENSE
fhir2transmart-0.2.1.dist-info/METADATA
fhir2transmart-0.2.1.dist-info/WHEEL
fhir2transmart-0.2.1.dist-info/entry_points.txt
fhir2transmart-0.2.1.dist-info/top_level.txt
fhir2transmart-0.2.1.dist-info/RECORD
