Metadata-Version: 2.1
Name: fhir2transmart
Version: 0.2.1
Summary: Example FHIR to TranSMART loader
Home-page: https://github.com/thehyve/python_fhir2transmart
Author: Gijs Kant
Author-email: gijs@thehyve.nl
License: GNU General Public License v3 or later
Keywords: fhir2transmart
Platform: UNKNOWN
Classifier: Development Status :: 2 - Pre-Alpha
Classifier: Intended Audience :: Developers
Classifier: Topic :: Scientific/Engineering :: Bio-Informatics
Classifier: License :: OSI Approved :: MIT License
Classifier: Natural Language :: English
Classifier: Programming Language :: Python :: 3
Classifier: Programming Language :: Python :: 3.6
Requires-Python: >=3.6.0
Requires-Dist: click (<8.0,>=7.0)
Requires-Dist: python-dateutil (==2.8.0)
Requires-Dist: fhirclient (==3.2.0)
Requires-Dist: transmart-loader (==1.3.5)
Provides-Extra: dev
Requires-Dist: prospector[with_pyroma] ; extra == 'dev'
Requires-Dist: yapf ; extra == 'dev'
Requires-Dist: isort ; extra == 'dev'
